cryptacular/__init__.py
cryptacular/bcrypt/__init__.py
cryptacular/bcrypt/test_bcrypt.py
cryptacular/core/__init__.py
cryptacular/core/test_core.py
cryptacular/crypt/__init__.py
cryptacular/crypt/test_crypt.py
cryptacular/pbkdf2/__init__.py
cryptacular/pbkdf2/test_pbkdf2.py
cryptacular/bcrypt/_bcrypt.cpython-37m-darwin.so.abi3.so
cryptacular-1.5.0.dist-info/METADATA
cryptacular-1.5.0.dist-info/WHEEL
cryptacular-1.5.0.dist-info/RECORD