Metadata-Version: 2.0
Name: cryptacular
Version: 1.5.0
Summary: A password hashing framework with bcrypt and pbkdf2.
Home-Page: http://bitbucket.org/dholth/cryptacular/
Author: Daniel Holth
Author-email: dholth@fastmail.fm
License: MIT
Keywords: bcrypt password security pbkdf2 crypt hash
Platform: UNKNOWN
Classifier: Development Status :: 5 - Production/Stable
Classifier: Intended Audience :: Developers
Classifier: Programming Language :: Python
Classifier: Programming Language :: Python :: 2
Classifier: Programming Language :: Python :: 2.7
Classifier: Programming Language :: Python :: 3
Classifier: Programming Language :: Python :: 3.5
Classifier: Programming Language :: Python :: Implementation :: CPython
Classifier: Programming Language :: Python :: Implementation :: PyPy
Classifier: Programming Language :: C
Classifier: Topic :: Security :: Cryptography
Provides-Extra: test
Requires-Dist: pytest ; extra == 'test'
Requires-Dist: pytest-cov ; extra == 'test'
Requires-Dist: pbkdf2
Requires-Dist: setuptools
